COPYING
README.md
setup.cfg
setup.py
filebytes/__init__.py
filebytes/binary.py
filebytes/ctypes_helper.py
filebytes/elf.py
filebytes/enum.py
filebytes/mach_o.py
filebytes/oat.py
filebytes/pe.py
filebytes.egg-info/PKG-INFO
filebytes.egg-info/SOURCES.txt
filebytes.egg-info/dependency_links.txt
filebytes.egg-info/top_level.txt