Metadata-Version: 2.1
Name: filebytes
Version: 0.9.20
Summary: Scripts to parse the following file formats - Executable and Linking Format (ELF), Portable Executable (PE), Mach-O and OAT (Android Runtime).
Home-page: https://scoding.de/filebytes-introduction/
Author: Sascha Schirra
Author-email: sashs@scoding.de
License: BSD-3-Clause
Platform: UNKNOWN
Classifier: Topic :: Security
Classifier: Environment :: Console
Classifier: Operating System :: OS Independent
Classifier: License :: OSI Approved :: BSD License
Classifier: Programming Language :: Python
Classifier: Intended Audience :: Developers
